json_part/__init__.py
json_part/json_part_parser.py
json_part-0.1.1.dist-info/LICENSE
json_part-0.1.1.dist-info/METADATA
json_part-0.1.1.dist-info/WHEEL
json_part-0.1.1.dist-info/RECORD
